{
   "android_play_store_link":"https://play.google.com/store/apps/details?id=com.astromobile.stickers.ajax",
   "ios_app_store_link":"",
   "sticker_packs":[
      {
         "identifier":"eredivisie2223f4a",
         "name":"vs Utrecht (1)",
         "animated_sticker_pack":false,
         "stickers":"18"
      },
      {
         "identifier":"eredivisie2223f4b",
         "name":"vs Utrecht (2)",
         "animated_sticker_pack":false,
         "stickers":"18"
      },
      {
         "identifier":"eredivisie2223f3",
         "name":"vs Sparta Rotterdam",
         "animated_sticker_pack":false,
         "stickers":"24"
      },
      {
         "identifier":"eredivisie2223f2",
         "name":"vs Groningen",
         "animated_sticker_pack":false,
         "stickers":"30"
      },
      {
         "identifier":"eredivisie2223f1",
         "name":"vs Sittard",
         "animated_sticker_pack":false,
         "stickers":"26"
      }
   ]
}